htpyp/__init__.py
htpyp/data/__init__.py
htpyp/data/ast.py
htpyp/data/token.py
htpyp/helpers/__init__.py
htpyp/helpers/exceptions.py
htpyp/helpers/str_helper.py
htpyp/lexer.py
htpyp/parser.py
htpyp/renderer.py
htpyp-0.1.dist-info/METADATA
htpyp-0.1.dist-info/WHEEL
htpyp-0.1.dist-info/RECORD
