Metadata-Version: 2.1
Name: htpyp
Version: 0.1
Summary: 
Author: Sven Keimpema
Requires-Python: >=3.10,<4.0
Classifier: Programming Language :: Python :: 3
Classifier: Programming Language :: Python :: 3.10
Classifier: Programming Language :: Python :: 3.11
